bemb/__init__.py
bemb/data/__init__.py
bemb/data/simulate_choice_dataset.py
bemb/model/__init__.py
bemb/model/_bemb_dev.py
bemb/model/_bemb_flex.py
bemb/model/bayesian_coefficient.py
bemb/model/bayesian_linear.py
bemb/model/bemb.py
bemb/model/bemb_flex_lightning.py
bemb/utils/__init__.py
bemb/utils/run_helper.py
bemb/utils/run_helper_lightning.py
bemb-0.1.7.dist-info/LICENSE
bemb-0.1.7.dist-info/METADATA
bemb-0.1.7.dist-info/WHEEL
bemb-0.1.7.dist-info/top_level.txt
bemb-0.1.7.dist-info/RECORD
