Metadata-Version: 2.1
Name: bemb
Version: 0.1.7
Summary: A Pytorch Backend Library for Choice Modelling with Bayesian Matrix Factorization
Home-page: 
Author: Tianyu Du
Author-email: tianyudu@stanford.edu
License: MIT
Classifier: License :: OSI Approved :: MIT License
Classifier: Programming Language :: Python :: 3
Classifier: Programming Language :: Python :: 3.8
License-File: LICENSE
